unique_color/__init__.py
unique_color/unique_color.py
unique_color-3.0.dist-info/LICENSE
unique_color-3.0.dist-info/METADATA
unique_color-3.0.dist-info/WHEEL
unique_color-3.0.dist-info/top_level.txt
unique_color-3.0.dist-info/RECORD
