Metadata-Version: 2.1
Name: unique-color
Version: 3.0
Summary: Provide 33 unique colors in hex or rgb format
Home-page: https://github.com/YichaoOU/unique_color
Author: Yichao Li
Author-email: yl079811@ohio.edu
License: LICENSE
Platform: UNKNOWN
